vidtool/__init__.py
vidtool/cli.py
vidtool/config.ini
vidtool/vidtool.py
vidtool/effects/__init__.py
vidtool/effects/transition.py
vidtool/mediainfo/__init__.py
vidtool/mediainfo/ffprobe_micro.py
vidtool/process/__init__.py
vidtool/process/reencode.py
vidtool/process/split.py
vidtool/reencode_plan/__init__.py
vidtool/reencode_plan/prefill.py
vidtool/reencode_plan/prefill_group.py
vidtool/reencode_plan/prefill_single.py
vidtool/reencode_plan/prefill_utils.py
vidtool/report/__init__.py
vidtool/report/report.py
vidtool/tools/__init__.py
vidtool/tools/tools.py
vidtool/utils/__init__.py
vidtool/utils/utils.py
vidtool-0.1.6.dist-info/AUTHORS.rst
vidtool-0.1.6.dist-info/LICENSE
vidtool-0.1.6.dist-info/METADATA
vidtool-0.1.6.dist-info/WHEEL
vidtool-0.1.6.dist-info/entry_points.txt
vidtool-0.1.6.dist-info/top_level.txt
vidtool-0.1.6.dist-info/RECORD
