Metadata-Version: 2.1
Name: vidtool
Version: 0.1.6
Summary: Smart optimization and join video files with minimum reencode process
Home-page: https://github.com/apenasrr/vidtool
Author: apenasrr
Author-email: apenasrr@gmail.com
License: MIT license
Keywords: vidtool
Classifier: Development Status :: 2 - Pre-Alpha
Classifier: Intended Audience :: Developers
Classifier: License :: OSI Approved :: MIT License
Classifier: Natural Language :: English
Classifier: Programming Language :: Python :: 3
Classifier: Programming Language :: Python :: 3.6
Classifier: Programming Language :: Python :: 3.7
Classifier: Programming Language :: Python :: 3.8
Requires-Python: >=3.6
License-File: LICENSE
License-File: AUTHORS.rst
Requires-Dist: Click (>=7.0)
Requires-Dist: natsort
Requires-Dist: unidecode
Requires-Dist: pandas
Requires-Dist: openpyxl
